angelsaechsisch_telegram/__init__.py
angelsaechsisch_telegram/__main__.py
angelsaechsisch_telegram/bot.py
angelsaechsisch_telegram/data/antworten.txt
angelsaechsisch_telegram/data/ausnahmen.txt
angelsaechsisch_telegram/data/de.txt
angelsaechsisch_telegram/data/google-10000-english.txt
angelsaechsisch_telegram/logik.py
angelsaechsisch_telegram-0.1.3.dist-info/LICENSE
angelsaechsisch_telegram-0.1.3.dist-info/WHEEL
angelsaechsisch_telegram-0.1.3.dist-info/METADATA
angelsaechsisch_telegram-0.1.3.dist-info/RECORD
